tap_pipedream/__init__.py
tap_pipedream/__main__.py
tap_pipedream/client.py
tap_pipedream/streams.py
tap_pipedream/tap.py
tap_pipedream-0.5.2.dist-info/METADATA
tap_pipedream-0.5.2.dist-info/WHEEL
tap_pipedream-0.5.2.dist-info/entry_points.txt
tap_pipedream-0.5.2.dist-info/licenses/LICENSE
tap_pipedream-0.5.2.dist-info/RECORD
