Metadata-Version: 2.4
Name: tap-pipedream
Version: 0.5.2
Summary: Singer tap for Pipedream, built with the Meltano SDK for Singer Taps.
Project-URL: Documentation, https://github.com/reservoir-data/tap-pipedream#readme
Project-URL: Homepage, https://github.com/reservoir-data/tap-pipedream
Project-URL: Repository, https://github.com/reservoir-data/tap-pipedream
Author-email: Edgar Ramírez-Mondragón <edgarrm358@gmail.com>
Maintainer-email: Edgar Ramírez-Mondragón <edgarrm358@gmail.com>
License-Expression: Apache-2.0
License-File: LICENSE
Keywords: ELT,Pipedream,singer.io
Classifier: Programming Language :: Python :: 3 :: Only
Classifier: Programming Language :: Python :: 3.11
Classifier: Programming Language :: Python :: 3.12
Classifier: Programming Language :: Python :: 3.13
Classifier: Programming Language :: Python :: 3.14
Requires-Python: >=3.11
Requires-Dist: singer-sdk~=0.52.5
